dcachefs/__init__.py
dcachefs/__version__.py
dcachefs/dcachefs.py
dcachefs-0.1.7.dist-info/LICENSE
dcachefs-0.1.7.dist-info/METADATA
dcachefs-0.1.7.dist-info/NOTICE
dcachefs-0.1.7.dist-info/WHEEL
dcachefs-0.1.7.dist-info/top_level.txt
dcachefs-0.1.7.dist-info/RECORD
