Metadata-Version: 2.1
Name: dcachefs
Version: 0.1.7
Summary: Python filesystem interface for dCache
Home-page: https://github.com/NLeSC-GO-common-infrastructure/dcachefs
Author: Francesco Nattino
Author-email: f.nattino@esciencecenter.nl
License: Apache Software License 2.0
Keywords: dcachefs
Platform: UNKNOWN
Classifier: Development Status :: 2 - Pre-Alpha
Classifier: Intended Audience :: Developers
Classifier: License :: OSI Approved :: Apache Software License
Classifier: Natural Language :: English
Classifier: Programming Language :: Python :: 3
Classifier: Programming Language :: Python :: 3.6
Classifier: Programming Language :: Python :: 3.7
Classifier: Programming Language :: Python :: 3.8
Requires-Dist: aiohttp
Requires-Dist: fsspec
Requires-Dist: urlpath
Requires-Dist: yarl
